dropt/client/__init__.py
dropt/client/endpoint.py
dropt/client/exception.py
dropt/client/interface.py
dropt/client/objects.py
dropt/client/requestor.py
dropt/client/resource.py
dropt/client/util.py
dropt/cmd/__init__.py
dropt/cmd/controller.py
dropt/cmd/launcher.py
dropt/cmd/util.py
dropt_cli-0.9.0.dist-info/AUTHORS.rst
dropt_cli-0.9.0.dist-info/LICENSE
dropt_cli-0.9.0.dist-info/METADATA
dropt_cli-0.9.0.dist-info/WHEEL
dropt_cli-0.9.0.dist-info/entry_points.txt
dropt_cli-0.9.0.dist-info/top_level.txt
dropt_cli-0.9.0.dist-info/RECORD
