Metadata-Version: 2.1
Name: dropt-cli
Version: 0.9.0
Summary: Library of DrOpt client
Home-page: https://github.com/GoEdge-ai/dropt-cli
Author: Chiayu Sun
Author-email: chiayusun.cs08g@nctu.edu.tw
License: MIT
Keywords: hyper-parameter,client,tuning
Platform: UNKNOWN
Classifier: Development Status :: 3 - Alpha
Classifier: Intended Audience :: Developers
Classifier: License :: OSI Approved :: MIT License
Classifier: Operating System :: OS Independent
Classifier: Environment :: Console
Classifier: Programming Language :: Python
Classifier: Programming Language :: Python :: 3.6
Classifier: Programming Language :: Python :: 3.7
Classifier: Programming Language :: Python :: 3.8
Classifier: Topic :: Software Development :: Libraries :: Python Modules
Requires-Python: >=3.6
Requires-Dist: setuptools (>=42.0.0)
Requires-Dist: requests (>=2.22.0)
Requires-Dist: questionary (>=1.5.2)
Requires-Dist: dropt-util (>=0.2)
